Metadata-Version: 2.1
Name: marchie
Version: 0.1
Summary: MarChie: a Compact Open Source Tool for Analyzing Discrete Markov Chains.
Home-page: https://github.com/maxschmaltz/MarChie
Author: Max Schmaltz
Author-email: schmaltzmax@gmail.com
License: Apache Software License
Keywords: markov chain,mathematics
Classifier: Development Status :: 4 - Beta
Classifier: License :: OSI Approved :: Apache Software License
Classifier: Topic :: Scientific/Engineering :: Mathematics
Classifier: Intended Audience :: Education
Classifier: Programming Language :: Python :: 3
Classifier: Programming Language :: Python :: 3.7
Classifier: Programming Language :: Python :: 3.8
Classifier: Programming Language :: Python :: 3.9
Classifier: Programming Language :: Python :: 3.10
Classifier: Programming Language :: Python :: 3 :: Only
License-File: LICENSE
